MANIFEST.in
README.txt
setup.py
MockProc.egg-info/PKG-INFO
MockProc.egg-info/SOURCES.txt
MockProc.egg-info/dependency_links.txt
MockProc.egg-info/not-zip-safe
MockProc.egg-info/top_level.txt
doc/Makefile
doc/conf.py
doc/index.rst
doc/mockproc.rst
mockproc/__init__.py
mockproc/mockprocess.py
mockproc/version.py
test/test_mockproc.py