Metadata-Version: 1.1
Name: MockProc
Version: 0.3.1
Summary: Simple stubs/mocks for processes (mostly for use with Nose)
Home-page: https://launchpad.net/mockproc
Author: Mike C. Fletcher
Author-email: mcfletch@vrplumber.com
License: BSD
Download-URL: http://pypi.python.org/pypi/MockProc/
Keywords: mock,process,subprocess
Platform: Any
Classifier: License :: OSI Approved :: BSD License
Classifier: Programming Language :: Python
Classifier: Topic :: Software Development :: Libraries :: Python Modules
Classifier: Intended Audience :: Developers
